aoirint_jmapy/__init__.py
aoirint_jmapy/api.py
aoirint_jmapy/const.py
aoirint_jmapy/static/__init__.py
aoirint_jmapy/static/const_telops.json
aoirint_jmapy/static/__pycache__/__init__.cpython-310.pyc
aoirint_jmapy-20220527.9.dist-info/LICENSE
aoirint_jmapy-20220527.9.dist-info/METADATA
aoirint_jmapy-20220527.9.dist-info/WHEEL
aoirint_jmapy-20220527.9.dist-info/top_level.txt
aoirint_jmapy-20220527.9.dist-info/RECORD
