Metadata-Version: 2.1
Name: aoirint-jmapy
Version: 20220527.9
Summary: Unofficial JMA weather forecast API wrapper in Python
Home-page: https://github.com/aoirint/aoirint_jmapy
Author: aoirint
Author-email: aoirint@gmail.com
License: UNKNOWN
Platform: UNKNOWN
Classifier: Development Status :: 3 - Alpha
Classifier: Programming Language :: Python
Classifier: Programming Language :: Python :: 3
Classifier: Programming Language :: Python :: 3.8
Classifier: Programming Language :: Python :: 3.9
License-File: LICENSE
Requires-Dist: requests
Requires-Dist: pydantic
